{
  "nodes": [
    {
      "id": "start",
      "text": "MC enters town. What does the MC choose to do?",
      "choices": [
        { "text": "Visit the market. Perhaps find missing gear or clues.", "target": "checkpoint_20" },
        { "text": "Head to the tavern. The bar is always full of gossip.", "target": "checkpoint_21" }
      ]
    },
    {
      "id": "checkpoint_20",
      "text": "Visit the market. Perhaps find missing gear or clues.",
      "choices": [
        { "text": "Speak to vendors about what they've seen or what they can offer.", "target": "checkpoint_201" },
        { "text": "Steal supplies from a vendor. Risk: Get caught. Reward: Get supplies", "target": "checkpoint_202" }
      ]
    },
    {
      "id": "checkpoint_2010",
      "text": "Speak to vendors about what they've seen or what they can offer.",
      "choices": [
        { "text": "Speak to Clara. The dueling champion of the town currently teaching villages how to fight.", "target": "checkpoint_2011" },
        { "text": "Speak to Luke. The owner of Luke's Blue Farm. Currently offering free samples of his local bread.", "target": "checkpoint_2012" }
      ]
    },
    {
      "id": "checkpoint_20110",
      "text": "Speak to Clara. The dueling champion of the town currently teaching villages how to fight.",
      "choices": [
        { "text": "Hello new friend, I'm providing weapons and teaching fighting techniques to those who might of encountered the beast. Come join me and I'll show you the proper way to fight", "target": "end" }
      ]
    },
    {
      "id": "checkpoint_20120",
      "text": "Speak to Luke. The owner of Luke's Blue Farm. Currently offering free samples of his local bread.",
      "choices": [
        { "text": "You're not from around here are you? Wait a minute, do you own that ship that crashed nearby? That was dangerously close to my farm, friend. Here take some supplies and make your way over. Stay safe", "target": "end" }
      ]
    },
    {
      "id": "checkpoint_2020", 
      "text": "Steal supplies from a vendor. Risk: Get caught. Reward: Get supplies",
      "choices": [
        { "text": "You get caught!", "target": "end" }
      ]
    },
    {
      "id": "checkpoint_2021",
      "text": "Steal supplies from a vendor. Risk: Get caught. Reward: Get supplies",
      "choices": [
        { "text": "You get succeed!", "target": "end" }
      ]
    },
    {
      "id": "checkpoint_21",
      "text": "Head to the tavern. The bar is always full of gossip from villagers.",
      "choices": [
        { "text": "Start a bar brawl to search for items to use in your next fight.", "target": "checkpoint_210" },
        { "text": "Buy a drink for the mysterious hidden figure. This could provide valuable insight or be a dangerous trap.", "target": "checkpoint_211" }
      ]
    },
    {
      "id": "checkpoint_2100",
      "text": "Start a bar brawl to search for items to use in your next fight.",
      "choices": [
        { "text": "Sneakily grab a glass bottle from the bar and throw it across the room.", "target": "checkpoint_21000" },
        { "text": "Shove the man next to you. Then point to the man to the other side of you.", "target": "checkpoint_21001" }
      ]
    },
    {
      "id": "checkpoint_21000",
      "text": "Sneakily grab a glass bottle from the bar and throw it across the room.",
      "choices": [
        { "text": "The bar tender Frank catches you and kicks you out!", "target": "end" },
        { "text": "A bar fight begins. While everyone is distracted you find the following: Your satchel near a strange mysterious person, but it only contains one small carving knife, and a letter in the backroom discussing a strange encounter the other day when something fell from the sky nearby.", "target": "end" }
      ]
    },
    {
      "id": "checkpoint_21001",
      "text": "Shove the man next to you. Then point to the man to the other side of you.",
      "choices": [
        { "text": "A bar fight begins. While everyone is distracted you find the following: Your satchel near a strange mysterious person, but it only contains one small carving knife, and a letter in the backroom discussing a strange encounter the other day when something fell from the sky nearby.", "target": "end" }
      ]
    },
    {
      "id": "end",
      "text": "You leave the town.",
      "choices": []
    }
  ]
}
